tom_alertstreams/__init__.py
tom_alertstreams/admin.py
tom_alertstreams/alertstreams/__init__.py
tom_alertstreams/alertstreams/alertstream.py
tom_alertstreams/alertstreams/gcn.py
tom_alertstreams/alertstreams/hopskotch.py
tom_alertstreams/apps.py
tom_alertstreams/management/commands/__init__.py
tom_alertstreams/management/commands/hoptestpub.py
tom_alertstreams/management/commands/readstreams.py
tom_alertstreams/migrations/__init__.py
tom_alertstreams/models.py
tom_alertstreams/tests.py
tom_alertstreams/views.py
tom_alertstreams-1.1.0.dist-info/METADATA
tom_alertstreams-1.1.0.dist-info/WHEEL
tom_alertstreams-1.1.0.dist-info/RECORD
