Metadata-Version: 2.4
Name: tom-alertstreams
Version: 1.1.0
Summary: Reusable TOMToolkit app for listening to kafka streams.
License-Expression: GPL-3.0-only
Keywords: tomtoolkit,astronomy,astrophysics,cosmology,science
Author: TOM Toolkit Project
Author-email: tomtoolkit-maintainers@lco.global
Maintainer: Joey Chatelain
Maintainer-email: jchate6@gmail.com
Requires-Python: >=3.9.0,<=3.13
Classifier: Environment :: Web Environment
Classifier: Framework :: Django
Classifier: Framework :: Django :: 4.1
Classifier: Intended Audience :: Developers
Classifier: Intended Audience :: Science/Research
Classifier: License :: OSI Approved :: GNU General Public License v3 or later (GPLv3+)
Classifier: Operating System :: OS Independent
Classifier: Programming Language :: Python
Classifier: Programming Language :: Python :: 3
Classifier: Programming Language :: Python :: 3 :: Only
Classifier: Programming Language :: Python :: 3.9
Classifier: Programming Language :: Python :: 3.10
Classifier: Programming Language :: Python :: 3.11
Classifier: Programming Language :: Python :: 3.12
Classifier: Programming Language :: Python :: 3.13
Classifier: Topic :: Scientific/Engineering :: Astronomy
Classifier: Topic :: Scientific/Engineering :: Physics
Requires-Dist: gcn-kafka (>=0.3,<1.0)
Requires-Dist: hop-client (>=0.10,<1.0)
Requires-Dist: psycopg2-binary (>=2.9,<3.0)
